pigpio.py
pigpio_autopilot-1.79.dist-info/METADATA
pigpio_autopilot-1.79.dist-info/WHEEL
pigpio_autopilot-1.79.dist-info/top_level.txt
pigpio_autopilot-1.79.dist-info/RECORD
