Metadata-Version: 2.1
Name: pigpio-autopilot
Version: 1.79
Summary: Raspberry Pi GPIO module - fork for use with autopilot
Home-page: http://abyz.me.uk/rpi/pigpio/python.html
Download-URL: https://github.com/sneakers-the-rat/pigpio/archive/refs/heads/master.zip
Author: joan
Author-email: joan@abyz.me.uk
Maintainer: joan
Maintainer-email: joan@abyz.me.uk
License: unlicense.org
Keywords: raspberrypi,gpio
Classifier: Programming Language :: Python :: 2
Classifier: Programming Language :: Python :: 3
